richka/__init__.py
richka/__main__.py
richka/__version__.py
richka/config.py
richka/controller.py
richka/core.py
richka-0.0.2.dist-info/LICENSE
richka-0.0.2.dist-info/METADATA
richka-0.0.2.dist-info/WHEEL
richka-0.0.2.dist-info/entry_points.txt
richka-0.0.2.dist-info/top_level.txt
richka-0.0.2.dist-info/RECORD
