Metadata-Version: 2.1
Name: richka
Version: 0.0.2
Summary: Python Async Download Engine.
Home-page: https://github.com/ghinknet/richka
Author: Ian Xia
Author-email: xia@ghink.net
License: MIT
Classifier: License :: OSI Approved :: MIT License
Classifier: Programming Language :: Python :: 3.9
Classifier: Programming Language :: Python :: 3.10
Classifier: Programming Language :: Python :: 3.11
Classifier: Programming Language :: Python :: 3.12
Classifier: Programming Language :: Python :: 3 :: Only
Requires-Python: >=3.9
License-File: LICENSE
Requires-Dist: aiohttp
